pyhunter/__init__.py
pyhunter/exceptions.py
pyhunter/pyhunter.py
pyhunter-0.3.dist-info/DESCRIPTION.rst
pyhunter-0.3.dist-info/METADATA
pyhunter-0.3.dist-info/RECORD
pyhunter-0.3.dist-info/WHEEL
pyhunter-0.3.dist-info/metadata.json
pyhunter-0.3.dist-info/top_level.txt
