Metadata-Version: 2.0
Name: pyhunter
Version: 0.3
Summary: An (unofficial) Python wrapper for the Hunter.io API
Home-page: https://github.com/VonStruddle/PyHunter
Author: Quentin Durantay
Author-email: quentin.durantay@gmail.com
License: MIT
Download-URL: https://github.com/VonStruddle/PyHunter/archive/0.3.tar.gz
Keywords: hunter,hunter.io,lead generation,lead enrichment
Platform: UNKNOWN
Classifier: Development Status :: 3 - Alpha
Classifier: Natural Language :: English
Classifier: License :: OSI Approved :: MIT License
Classifier: Programming Language :: Python
Classifier: Programming Language :: Python :: 3
Classifier: Programming Language :: Python :: 3.3
Classifier: Programming Language :: Python :: 3.4
Classifier: Programming Language :: Python :: 3.5
Classifier: Topic :: Utilities
Requires-Dist: requests
